log_analyzer_cwj/__init__.py
log_analyzer_cwj/analyzer.py
log_analyzer_cwj/hello.py
log_analyzer_cwj/innerRule.cp310-win_amd64.pyd
log_analyzer_cwj/logAnalyzer.cp310-win_amd64.pyd
log_analyzer_cwj-0.0.44.dist-info/METADATA
log_analyzer_cwj-0.0.44.dist-info/WHEEL
log_analyzer_cwj-0.0.44.dist-info/top_level.txt
log_analyzer_cwj-0.0.44.dist-info/RECORD
