Metadata-Version: 2.1
Name: log-analyzer-cwj
Version: 0.0.44
Summary: log analyze
Home-page: https://github.com/SystemLight/madtornado
Download-URL: https://github.com/SystemLight/madtornado/releases
Author: chenwenjun
Author-email: cwj129@126.com
License: apache 3.0
Requires: numpy
Requires: matplotlib
